tabpfnwide/__init__.py
tabpfnwide/classifier.py
tabpfnwide/config.py
tabpfnwide/patches.py
tabpfnwide-0.1.0.dist-info/licenses/LICENSE
tabpfnwide-0.1.0.dist-info/METADATA
tabpfnwide-0.1.0.dist-info/WHEEL
tabpfnwide-0.1.0.dist-info/top_level.txt
tabpfnwide-0.1.0.dist-info/RECORD
