Metadata-Version: 2.4
Name: tabpfnwide
Version: 0.1.0
Summary: TabPFN-Wide: Extension of the TabPFN-2 foundation model, specifically designed for wide datasets (many features, few samples).
Author: Jules Kreuer, Christopher Kolberg, Jonas Huurdeman, Sofiane Ouaari, Katharina Eggensperger, Nico Pfeifer
License: Prior Labs License Version 1.1
Project-URL: Homepage, https://github.com/not-a-feature/TabPFN-Wide
Project-URL: Repository, https://github.com/not-a-feature/TabPFN-Wide
Project-URL: Bug Tracker, https://github.com/not-a-feature/TabPFN-Wide/issues
Keywords: tabpfn,tabular,machine-learning,multi-omics,foundation-model,wide-data
Classifier: Programming Language :: Python :: 3
Classifier: Programming Language :: Python :: 3.10
Classifier: Programming Language :: Python :: 3.11
Classifier: Programming Language :: Python :: 3.12
Classifier: Intended Audience :: Science/Research
Classifier: Topic :: Scientific/Engineering :: Artificial Intelligence
Requires-Python: >=3.10
License-File: LICENSE
Requires-Dist: numpy
Requires-Dist: scikit-learn
Requires-Dist: scipy
Requires-Dist: torch
Requires-Dist: tabpfn==6.0.6
Provides-Extra: dev
Requires-Dist: pandas; extra == "dev"
Requires-Dist: tqdm; extra == "dev"
Requires-Dist: wandb; extra == "dev"
Requires-Dist: tabicl; extra == "dev"
Requires-Dist: openml; extra == "dev"
Requires-Dist: matplotlib; extra == "dev"
Requires-Dist: seaborn; extra == "dev"
Requires-Dist: scipy; extra == "dev"
Dynamic: license-file
